odoo8_addon_l10n_br_sale-8.0.1.0.0.99.dev25-py2.7-nspkg.pth
odoo8_addon_l10n_br_sale-8.0.1.0.0.99.dev25.dist-info/top_level.txt
odoo8_addon_l10n_br_sale-8.0.1.0.0.99.dev25.dist-info/WHEEL
odoo8_addon_l10n_br_sale-8.0.1.0.0.99.dev25.dist-info/RECORD
odoo8_addon_l10n_br_sale-8.0.1.0.0.99.dev25.dist-info/metadata.json
odoo8_addon_l10n_br_sale-8.0.1.0.0.99.dev25.dist-info/DESCRIPTION.rst
odoo8_addon_l10n_br_sale-8.0.1.0.0.99.dev25.dist-info/METADATA
odoo8_addon_l10n_br_sale-8.0.1.0.0.99.dev25.dist-info/namespace_packages.txt
odoo_addons/l10n_br_sale/__openerp__.py
odoo_addons/l10n_br_sale/__init__.py
odoo_addons/l10n_br_sale/README.rst
odoo_addons/l10n_br_sale/security/l10n_br_sale_security.xml
odoo_addons/l10n_br_sale/security/ir.model.access.csv
odoo_addons/l10n_br_sale/report/__init__.py
odoo_addons/l10n_br_sale/report/sale_report.py
odoo_addons/l10n_br_sale/report/sale_report_view.xml
odoo_addons/l10n_br_sale/models/res_config.py
odoo_addons/l10n_br_sale/models/sale.py
odoo_addons/l10n_br_sale/models/__init__.py
odoo_addons/l10n_br_sale/models/res_company.py
odoo_addons/l10n_br_sale/i18n/pt_BR.po
odoo_addons/l10n_br_sale/wizard/__init__.py
odoo_addons/l10n_br_sale/wizard/sale_make_invoice_advanced_percentage.py
odoo_addons/l10n_br_sale/views/sale_view.xml
odoo_addons/l10n_br_sale/views/res_config_view.xml
odoo_addons/l10n_br_sale/data/l10n_br_sale_data.xml
odoo_addons/l10n_br_sale/static/description/icon.png
