Metadata-Version: 2.0
Name: odoo8-addon-l10n-br-sale
Version: 8.0.1.0.0.99.dev25
Summary: Brazilian Localization Sale
Home-page: http://odoo-brasil.org
Author: UNKNOWN
Author-email: UNKNOWN
License: AGPL-3
Platform: UNKNOWN
Requires-Dist: odoo (<9.0a,>=8.0a)
Requires-Dist: odoo8-addon-account-fiscal-position-rule-sale
Requires-Dist: odoo8-addon-l10n-br-account
Classifier: Programming Language :: Python :: 2.7
Classifier: Framework :: Odoo
Classifier: License :: OSI Approved :: GNU Affero General Public License v3
